Workbook
Name Slicer_Category: #N/A
Name Slicer_Month_name: #N/A
Name Slicer_Region: #N/A

Sheet Pivot tables
A3: Row Labels | B3: Sum of FinalPrice | C3: Row Labels | D3: Sum of FinalPrice | E3: Row Labels | F3: Sum of FinalPrice | G3: Row Labels | H3: Sum of FinalPrice
A4: Faisalabad | B4: 16109775 | C4: January | D4: 9020225 | E4: Sara | F4: 16020275 | G4: Faisalabad | H4: 16109775
A5: Charger | B5: 1726750 | C5: February | D5: 9395325 | E5: Ali | F5: 15243825 | G5: Islamabad | H5: 10997300
A6: Headphone | B6: 2706475 | C6: March | D6: 14801725 | E6: Bilal | F6: 14549800 | G6: Karachi | H6: 16120625
A7: Keyboard | B7: 2525800 | C7: April | D7: 11302975 | E7: Fatima | F7: 13403550 | G7: Lahore | H7: 13704875
A8: Laptop | B8: 1201625 | C8: May | D8: 11194575 | E8: Ahmed | F8: 13075275 | G8: Multan | H8: 19777400
A9: Mobile | B9: 1450850 | C9: June | D9: 10377225 | E9: Usman | F9: 11696525 | G9: Peshawar | H9: 17526700
A10: Monitor | B10: 2480250 | C10: July | D10: 2800375 | E10: Ayesha | F10: 10247425 | G10: Grand Total | H10: 94236675
A11: Mouse | B11: 2572250 | C11: August | D11: 7226350 | E11: Grand Total | F11: 94236675
A12: Tablet | B12: 1445775 | C12: September | D12: 5568050
A13: Islamabad | B13: 10997300 | C13: October | D13: 4330875 | G13: Total Profit | H13: Total Order
A14: Charger | B14: 725000 | C14: November | D14: 5504100 | E14: Total Sales | G14: 48252975 | H14: 500
A15: Headphone | B15: 1192100 | C15: December | D15: 2714875 | E15: 94236675 | J15: Sum of Profit
A16: Keyboard | B16: 167050 | C16: Grand Total | D16: 94236675 | F16: Total Quantity | J16: 48252975
A17: Laptop | B17: 2730575 | F17: 2500
A18: Mobile | B18: 817600
A19: Monitor | B19: 1848625
A20: Mouse | B20: 2258125
A21: Tablet | B21: 1258225
A22: Karachi | B22: 16120625
A23: Charger | B23: 1295750
A24: Headphone | B24: 3326900
A25: Keyboard | B25: 3751500
A26: Laptop | B26: 1041150
A27: Mobile | B27: 474650
A28: Monitor | B28: 1583375
A29: Mouse | B29: 2702050
... A58: Grand Total | B58: 94236675

Sheet Dashboard

Sheet Sales_Data
A1: OrderID | B1: Date | C1: Month name | D1: Year | E1: Product | F1: Category | G1: Region | H1: SalesPerson | I1: Quantity | J1: UnitPrice | K1: Discount% | L1: TotalPrice | M1: FinalPrice | N1: Profit | O1: Discount category | P1: Cost price
A2: ORD-1126 | B2: 45292 | C2: =TEXT(B2,"MMMM") -> January | D2: =TEXT(B2,"yyy") -> 2024 | E2: Mobile | F2: Electronics | G2: Islamabad | H2: Bilal | I2: 9 | J2: 1500 | K2: 10 | L2: 13500 | M2: 12150 | N2: =(M2-P2)*I2 -> -205650 | O2: =IF(K2=15%,"Very High ",IF(K2=10%,"High Discount","Normal")) -> Normal | P2: =_xlfn.XLOOKUP(E2,Products_Master!B:B,Products_Master!D:D) -> 35000
A3: ORD-1405 | B3: 45292 | C3: =TEXT(B3,"MMMM") -> January | D3: =TEXT(B3,"yyy") -> 2024 | E3: Headphone | F3: Accessories | G3: Peshawar | H3: Bilal | I3: 3 | J3: 45000 | K3: 10 | L3: 135000 | M3: 121500 | N3: =(M3-P3)*I3 -> 358500 | O3: =IF(K3=15%,"Very High ",IF(K3=10%,"High Discount","Normal")) -> Normal | P3: =_xlfn.XLOOKUP(E3,Products_Master!B:B,Products_Master!D:D) -> 2000
A4: ORD-1382 | B4: 45293 | C4: =TEXT(B4,"MMMM") -> January | D4: =TEXT(B4,"yyy") -> 2024 | E4: Headphone | F4: Electronics | G4: Faisalabad | H4: Bilal | I4: 5 | J4: 15000 | K4: 0 | L4: 75000 | M4: 75000 | N4: =(M4-P4)*I4 -> 365000 | O4: =IF(K4=15%,"Very High ",IF(K4=10%,"High Discount","Normal")) -> Normal | P4: =_xlfn.XLOOKUP(E4,Products_Master!B:B,Products_Master!D:D) -> 2000
A5: ORD-1221 | B5: 45294 | C5: =TEXT(B5,"MMMM") -> January | D5: =TEXT(B5,"yyy") -> 2024 | E5: Tablet | F5: Electronics | G5: Lahore | H5: Ali | I5: 3 | J5: 1500 | K5: 0 | L5: 4500 | M5: 4500 | N5: =(M5-P5)*I5 -> -40500 | O5: =IF(K5=15%,"Very High ",IF(K5=10%,"High Discount","Normal")) -> Normal | P5: =_xlfn.XLOOKUP(E5,Products_Master!B:B,Products_Master!D:D) -> 18000
A6: ORD-1114 | B6: 45295 | C6: =TEXT(B6,"MMMM") -> January | D6: =TEXT(B6,"yyy") -> 2024 | E6: Keyboard | F6: Accessories | G6: Peshawar | H6: Bilal | I6: 5 | J6: 15000 | K6: 0 | L6: 75000 | M6: 75000 | N6: =(M6-P6)*I6 -> 370500 | O6: =IF(K6=15%,"Very High ",IF(K6=10%,"High Discount","Normal")) -> Normal | P6: =_xlfn.XLOOKUP(E6,Products_Master!B:B,Products_Master!D:D) -> 900
A7: ORD-1304 | B7: 45295 | C7: =TEXT(B7,"MMMM") -> January | D7: =TEXT(B7,"yyy") -> 2024 | E7: Mobile | F7: Accessories | G7: Peshawar | H7: Fatima | I7: 9 | J7: 8000 | K7: 10 | L7: 72000 | M7: 64800 | N7: =(M7-P7)*I7 -> 268200 | O7: =IF(K7=15%,"Very High ",IF(K7=10%,"High Discount","Normal")) -> Normal | P7: =_xlfn.XLOOKUP(E7,Products_Master!B:B,Products_Master!D:D) -> 35000
A8: ORD-1441 | B8: 45297 | C8: =TEXT(B8,"MMMM") -> January | D8: =TEXT(B8,"yyy") -> 2024 | E8: Monitor | F8: Electronics | G8: Peshawar | H8: Ayesha | I8: 7 | J8: 8000 | K8: 0 | L8: 56000 | M8: 56000 | N8: =(M8-P8)*I8 -> 287000 | O8: =IF(K8=15%,"Very High ",IF(K8=10%,"High Discount","Normal")) -> Normal | P8: =_xlfn.XLOOKUP(E8,Products_Master!B:B,Products_Master!D:D) -> 15000
A9: ORD-1496 | B9: 45298 | C9: =TEXT(B9,"MMMM") -> January | D9: =TEXT(B9,"yyy") -> 2024 | E9: Tablet | F9: Electronics | G9: Faisalabad | H9: Ahmed | I9: 9 | J9: 1500 | K9: 15 | L9: 13500 | M9: 11475 | N9: =(M9-P9)*I9 -> -58725 | O9: =IF(K9=15%,"Very High ",IF(K9=10%,"High Discount","Normal")) -> Normal | P9: =_xlfn.XLOOKUP(E9,Products_Master!B:B,Products_Master!D:D) -> 18000
A10: ORD-1021 | B10: 45298 | C10: =TEXT(B10,"MMMM") -> January | D10: =TEXT(B10,"yyy") -> 2024 | E10: Charger | F10: Electronics | G10: Karachi | H10: Ahmed | I10: 2 | J10: 2500 | K10: 5 | L10: 5000 | M10: 4750 | N10: =(M10-P10)*I10 -> 7900 | O10: =IF(K10=15%,"Very High ",IF(K10=10%,"High Discount","Normal")) -> Normal | P10: =_xlfn.XLOOKUP(E10,Products_Master!B:B,Products_Master!D:D) -> 800
A11: ORD-1163 | B11: 45299 | C11: =TEXT(B11,"MMMM") -> January | D11: =TEXT(B11,"yyy") -> 2024 | E11: Headphone | F11: Accessories | G11: Multan | H11: Usman | I11: 9 | J11: 120000 | K11: 0 | L11: 1080000 | M11: 1080000 | N11: =(M11-P11)*I11 -> 9702000 | O11: =IF(K11=15%,"Very High ",IF(K11=10%,"High Discount","Normal")) -> Normal | P11: =_xlfn.XLOOKUP(E11,Products_Master!B:B,Products_Master!D:D) -> 2000
A12: ORD-1282 | B12: 45300 | C12: =TEXT(B12,"MMMM") -> January | D12: =TEXT(B12,"yyy") -> 2024 | E12: Mouse | F12: Accessories | G12: Karachi | H12: Fatima | I12: 6 | J12: 15000 | K12: 10 | L12: 90000 | M12: 81000 | N12: =(M12-P12)*I12 -> 482400 | O12: =IF(K12=15%,"Very High ",IF(K12=10%,"High Discount","Normal")) -> Normal | P12: =_xlfn.XLOOKUP(E12,Products_Master!B:B,Products_Master!D:D) -> 600
A13: ORD-1266 | B13: 45301 | C13: =TEXT(B13,"MMMM") -> January | D13: =TEXT(B13,"yyy") -> 2024 | E13: Headphone | F13: Electronics | G13: Multan | H13: Bilal | I13: 6 | J13: 120000 | K13: 5 | L13: 720000 | M13: 684000 | N13: =(M13-P13)*I13 -> 4092000 | O13: =IF(K13=15%,"Very High ",IF(K13=10%,"High Discount","Normal")) -> Normal | P13: =_xlfn.XLOOKUP(E13,Products_Master!B:B,Products_Master!D:D) -> 2000
... A501: ORD-1145 | B501: 45832 | C501: =TEXT(B501,"MMMM") -> June | D501: =TEXT(B501,"yyy") -> 2025 | E501: Keyboard | F501: Electronics | G501: Faisalabad | H501: Ayesha | I501: 4 | J501: 2500 | K501: 0 | L501: 10000 | M501: 10000 | N501: =(M501-P501)*I501 -> 36400 | O501: =IF(K501=15%,"Very High ",IF(K501=10%,"High Discount","Normal")) -> Normal | P501: =_xlfn.XLOOKUP(E501,Products_Master!B:B,Products_Master!D:D) -> 900

Sheet Employee_Data
A1: EmpID | B1: Name | C1: Department | D1: JoiningDate | E1: Salary | F1: PerformanceScore | G1: City | H1: Experience | I1: Departmnt Names | J1: Employee Count | K1: AVRG sallery
A2: EMP-1 | B2: Employee_1 | C2: IT | D2: 44689 | E2: 177416 | F2: 4 | G2: Islamabad | H2: =DATEDIF(D2,TODAY(),"Y") -> 4 | I2: IT | J2: =COUNTIF(C:C,I2) -> 24 | K2: =AVERAGEIF(C:C,I2,E:E) -> 125649.42
A3: EMP-2 | B3: Employee_2 | C3: Finance | D3: 44933 | E3: 58800 | F3: 5 | G3: Peshawar | H3: =DATEDIF(D3,TODAY(),"Y") -> 3 | I3: Finance | J3: =COUNTIF(C:C,I3) -> 21 | K3: =AVERAGEIF(C:C,I3,E:E) -> 131997.86
A4: EMP-3 | B4: Employee_3 | C4: Marketing | D4: 44949 | E4: 65372 | F4: 1 | G4: Karachi | H4: =DATEDIF(D4,TODAY(),"Y") -> 3 | I4: Marketing | J4: =COUNTIF(C:C,I4) -> 19 | K4: =AVERAGEIF(C:C,I4,E:E) -> 118246
A5: EMP-4 | B5: Employee_4 | C5: Finance | D5: 45066 | E5: 101516 | F5: 1 | G5: Karachi | H5: =DATEDIF(D5,TODAY(),"Y") -> 3 | I5: Sales | J5: =COUNTIF(C:C,I5) -> 16 | K5: =AVERAGEIF(C:C,I5,E:E) -> 101400.25
A6: EMP-5 | B6: Employee_5 | C6: IT | D6: 44282 | E6: 60538 | F6: 1 | G6: Karachi | H6: =DATEDIF(D6,TODAY(),"Y") -> 5 | I6: HR | J6: =COUNTIF(C:C,I6) -> 20 | K6: =AVERAGEIF(C:C,I6,E:E) -> 123484.05
A7: EMP-6 | B7: Employee_6 | C7: Marketing | D7: 44830 | E7: 103918 | F7: 1 | G7: Faisalabad | H7: =DATEDIF(D7,TODAY(),"Y") -> 4
A8: EMP-7 | B8: Employee_7 | C8: Sales | D8: 44280 | E8: 186045 | F8: 3 | G8: Lahore | H8: =DATEDIF(D8,TODAY(),"Y") -> 5
A9: EMP-8 | B9: Employee_8 | C9: Sales | D9: 44389 | E9: 111155 | F9: 3 | G9: Islamabad | H9: =DATEDIF(D9,TODAY(),"Y") -> 5
A10: EMP-9 | B10: Employee_9 | C10: HR | D10: 44723 | E10: 99500 | F10: 3 | G10: Lahore | H10: =DATEDIF(D10,TODAY(),"Y") -> 4
A11: EMP-10 | B11: Employee_10 | C11: IT | D11: 44825 | E11: 150659 | F11: 5 | G11: Lahore | H11: =DATEDIF(D11,TODAY(),"Y") -> 4
A12: EMP-11 | B12: Employee_11 | C12: IT | D12: 43890 | E12: 67716 | F12: 5 | G12: Lahore | H12: =DATEDIF(D12,TODAY(),"Y") -> 6
A13: EMP-12 | B13: Employee_12 | C13: Sales | D13: 44627 | E13: 174308 | F13: 5 | G13: Karachi | H13: =DATEDIF(D13,TODAY(),"Y") -> 4
A14: EMP-13 | B14: Employee_13 | C14: Finance | D14: 44519 | E14: 186920 | F14: 2 | G14: Multan | H14: =DATEDIF(D14,TODAY(),"Y") -> 4
A15: EMP-14 | B15: Employee_14 | C15: Marketing | D15: 45200 | E15: 42352 | F15: 5 | G15: Karachi | H15: =DATEDIF(D15,TODAY(),"Y") -> 3
A16: EMP-15 | B16: Employee_15 | C16: Finance | D16: 45221 | E16: 173004 | F16: 3 | G16: Karachi | H16: =DATEDIF(D16,TODAY(),"Y") -> 2
A17: EMP-16 | B17: Employee_16 | C17: Finance | D17: 44659 | E17: 116449 | F17: 3 | G17: Peshawar | H17: =DATEDIF(D17,TODAY(),"Y") -> 4
A18: EMP-17 | B18: Employee_17 | C18: Sales | D18: 45314 | E18: 48556 | F18: 2 | G18: Peshawar | H18: =DATEDIF(D18,TODAY(),"Y") -> 2
... A101: EMP-100 | B101: Employee_100 | C101: Marketing | D101: 45232 | E101: 88456 | F101: 2 | G101: Peshawar | H101: =DATEDIF(D101,TODAY(),"Y") -> 2

Sheet Products_Master
A1: ProductID | B1: ProductName | C1: Category | D1: CostPrice
A2: P001 | B2: Laptop | C2: Electronics | D2: 70000
A3: P002 | B3: Mobile | C3: Electronics | D3: 35000
A4: P003 | B4: Tablet | C4: Electronics | D4: 18000
A5: P004 | B5: Headphone | C5: Accessories | D5: 2000
A6: P005 | B6: Charger | C6: Accessories | D6: 800
A7: P006 | B7: Mouse | C7: Accessories | D7: 600
A8: P007 | B8: Keyboard | C8: Accessories | D8: 900
A9: P008 | B9: Monitor | C9: Electronics | D9: 15000

Sheet Customers_Master
A1: CustomerID | B1: CustomerName | C1: Region | D1: CustomerType
A2: CUST-0001 | B2: Customer_1 | C2: Lahore | D2: Online
A3: CUST-0002 | B3: Customer_2 | C3: Islamabad | D3: Wholesale
A4: CUST-0003 | B4: Customer_3 | C4: Multan | D4: Wholesale
A5: CUST-0004 | B5: Customer_4 | C5: Multan | D5: Retail
A6: CUST-0005 | B6: Customer_5 | C6: Multan | D6: Online
A7: CUST-0006 | B7: Customer_6 | C7: Karachi | D7: Retail
A8: CUST-0007 | B8: Customer_7 | C8: Lahore | D8: Retail
A9: CUST-0008 | B9: Customer_8 | C9: Islamabad | D9: Wholesale
A10: CUST-0009 | B10: Customer_9 | C10: Karachi | D10: Online
A11: CUST-0010 | B11: Customer_10 | C11: Faisalabad | D11: Online
A12: CUST-0011 | B12: Customer_11 | C12: Islamabad | D12: Online
... A201: CUST-0200 | B201: Customer_200 | C201: Islamabad | D201: Retail
